smart_generator/__init__.py
smart_generator/generator_factory.py
smart_generator/descriptor/__init__.py
smart_generator/descriptor/behaviour.py
smart_generator/descriptor/column.py
smart_generator/descriptor/descriptor.py
smart_generator/descriptor/enums.py
smart_generator/descriptor/sequence.py
smart_generator/descriptor/table_descriptor.py
smart_generator/generator/__init__.py
smart_generator/generator/column_generator.py
smart_generator/generator/column_generator_exponential_distribution.py
smart_generator/generator/column_generator_increment.py
smart_generator/generator/column_generator_normal_distribution.py
smart_generator/generator/column_generator_template.py
smart_generator/generator/column_generator_template_geolocation.py
smart_generator/generator/column_generator_template_label.py
smart_generator/generator/column_generator_template_timeseries.py
smart_generator/generator/column_generator_template_timestamp.py
smart_generator/generator/column_generator_uniform_distribution.py
smart_generator/generator/column_generator_unique.py
smart_generator/generator/column_generator_weights_table.py
smart_generator/generator/column_metadata.py
smart_generator/generator/sequence_generator.py
smart_generator/generator/sequence_generator_loop.py
smart_generator/generator/sequence_generator_loop_random.py
smart_generator/generator/sequence_generator_template.py
smart_generator/generator/table_generator.py
smart_generator/helpers/__init__.py
smart_generator/helpers/args_convertion.py
smart_generator/helpers/columns_combinations.py
smart_generator/helpers/datetime_precision.py
smart_generator/helpers/merging_filters.py
smart_generator/helpers/template_column_naming.py
smart_generator/helpers/timeseries_coding.py
smart_generator/templates/__init__.py
smart_generator/templates/enums.py
smart_generator/templates/template_table.py
smart_generator/templates/templates_provider.py
smart_generator/templates/templates_provider_dataframe.py
smart_generator-0.9.1.dist-info/LICENSE
smart_generator-0.9.1.dist-info/METADATA
smart_generator-0.9.1.dist-info/WHEEL
smart_generator-0.9.1.dist-info/top_level.txt
smart_generator-0.9.1.dist-info/RECORD
