Metadata-Version: 2.1
Name: smart-generator
Version: 0.9.1
Summary: Test data generator library
Author-email: Peter Kratky <kratky.peto@gmail.com>
Classifier: Programming Language :: Python :: 3
Classifier: Programming Language :: Python :: 3.10
Classifier: Programming Language :: Python :: 3.11
Classifier: Programming Language :: Python :: 3.12
Classifier: Intended Audience :: Developers
Classifier: License :: OSI Approved :: MIT License
Classifier: Operating System :: OS Independent
Requires-Python: >=3.10
License-File: LICENSE
Requires-Dist: marshmallow-dataclass >=8.5.14
Requires-Dist: typeguard >=3.0.0
Requires-Dist: pandas >=1.4.0
Requires-Dist: cachetools >=5.0.0
Requires-Dist: sqlalchemy
Requires-Dist: exrex
